simplepyq/__init__.py
simplepyq/simplepyq.py
simplepyq-0.1.3.dist-info/licenses/LICENSE
tests/__init__.py
tests/test_simplepyq.py
simplepyq-0.1.3.dist-info/METADATA
simplepyq-0.1.3.dist-info/WHEEL
simplepyq-0.1.3.dist-info/top_level.txt
simplepyq-0.1.3.dist-info/RECORD
