Metadata-Version: 2.4
Name: simplepyq
Version: 0.1.3
Summary: A lightweight task scheduler
Home-page: https://github.com/kdewald/simplepyq
Author: Kevin Dewald
Author-email: kevin@dewald.me
License: Apache-2.0
Classifier: Programming Language :: Python :: 3
Classifier: License :: OSI Approved :: Apache Software License
Classifier: Operating System :: OS Independent
Requires-Python: >=3.6
License-File: LICENSE
Requires-Dist: msgpack
Dynamic: author
Dynamic: author-email
Dynamic: classifier
Dynamic: description
Dynamic: description-content-type
Dynamic: home-page
Dynamic: license
Dynamic: license-file
Dynamic: requires-dist
Dynamic: requires-python
Dynamic: summary
